Metadata-Version: 2.1
Name: lib_dzne_numeral
Version: 0.1.0
Summary: Libary for handling numerals.
Author-email: Johannes Horler <johannes.horler@dzne.de>
License: Copyright © 2022 Johannes Horler
Classifier: License :: OSI Approved :: MIT License
Classifier: Programming Language :: Python
Classifier: Programming Language :: Python :: 3
Requires-Python: >=3.11
License-File: LICENSE
